ccdprocx/__init__.py
ccdprocx/_astropy_init.py
ccdprocx/ccddata.py
ccdprocx/combiner.py
ccdprocx/conftest.py
ccdprocx/core.py
ccdprocx/image_collection.py
ccdprocx/log_meta.py
ccdprocx/version.py
ccdprocx/version_alt.py
ccdprocx/version_gen.py
ccdprocx/extern/__init__.py
ccdprocx/extern/bitfield.py
ccdprocx/tests/__init__.py
ccdprocx/tests/make_mef.py
ccdprocx/tests/pytest_fixtures.py
ccdprocx/tests/run_for_memory_profile.py
ccdprocx/tests/run_with_file_number_limit.py
ccdprocx/tests/test_bitfield.py
ccdprocx/tests/test_ccdmask.py
ccdprocx/tests/test_ccdproc.py
ccdprocx/tests/test_ccdproc_logging.py
ccdprocx/tests/test_combine_open_files.py
ccdprocx/tests/test_combiner.py
ccdprocx/tests/test_cosmicray.py
ccdprocx/tests/test_gain.py
ccdprocx/tests/test_image_collection.py
ccdprocx/tests/test_keyword.py
ccdprocx/tests/test_memory_use.py
ccdprocx/tests/test_rebin.py
ccdprocx/tests/test_wrapped_external_funcs.py
ccdprocx/tests/data/README.rst
ccdprocx/tests/data/a8280271.fits
ccdprocx/tests/data/expected_ifc_file_properties.csv
ccdprocx/tests/data/flat-mef.fits
ccdprocx/tests/data/science-mef.fits
ccdprocx/tests/data/sip-wcs.fit
ccdprocx/utils/__init__.py
ccdprocx/utils/sample_directory.py
ccdprocx/utils/slices.py
ccdprocx/utils/tests/__init__.py
ccdprocx/utils/tests/test_slices.py
ccdprocx-2.2.1.dev7.dist-info/AUTHORS.rst
ccdprocx-2.2.1.dev7.dist-info/LICENSE.rst
ccdprocx-2.2.1.dev7.dist-info/METADATA
ccdprocx-2.2.1.dev7.dist-info/WHEEL
ccdprocx-2.2.1.dev7.dist-info/top_level.txt
ccdprocx-2.2.1.dev7.dist-info/RECORD
